{"v":"5.5.7","meta":{"g":"LottieFiles AE 0.1.21","a":"SJGmotion","k":"Loader, Loading, Circle, Repeat, Loop","d":"Gradient Circle Loader","tc":""},"fr":30,"ip":0,"op":61,"w":1080,"h":1080,"nm":"Loader1","ddd":0,"assets":[],"layers":[{"ddd":0,"ind":1,"ty":4,"nm":"Circle_Inner 1","sr":1,"ks":{"o":{"a":0,"k":100,"ix":11},"r":{"a":0,"k":0,"ix":10},"p":{"a":1,"k":[{"i":{"x":0.833,"y":0.833},"o":{"x":0.333,"y":0},"t":0,"s":[540.186,340.8,0],"to":[-109.455,0,0],"ti":[0,-109.455,0]},{"i":{"x":0.833,"y":0.833},"o":{"x":0.167,"y":0.167},"t":11,"s":[342,538.986,0],"to":[0,109.455,0],"ti":[-109.455,0,0]},{"i":{"x":0.833,"y":0.833},"o":{"x":0.167,"y":0.167},"t":22,"s":[540.186,737.172,0],"to":[109.455,0,0],"ti":[0,109.455,0]},{"i":{"x":0.728,"y":1},"o":{"x":0.167,"y":0.167},"t":33,"s":[738.372,538.986,0],"to":[0,-109.455,0],"ti":[109.455,0,0]},{"t":44,"s":[540.186,340.8,0]}],"ix":2},"a":{"a":0,"k":[9.351,-77.955,0],"ix":1},"s":{"a":0,"k":[60,60,100],"ix":6}},"ao":0,"shapes":[{"ty":"gr","it":[{"d":1,"ty":"el","s":{"a":0,"k":[150,150],"ix":2},"p":{"a":0,"k":[0,0],"ix":3},"nm":"Ellipse Path 1","mn":"ADBE Vector Shape - Ellipse","hd":false},{"ty":"gf","o":{"a":0,"k":100,"ix":10},"r":1,"bm":0,"g":{"p":3,"k":{"a":0,"k":[0,1,0.637,0,0.5,0.998,0.529,0.089,1,0.996,0.421,0.177],"ix":9}},"s":{"a":1,"k":[{"i":{"x":0.833,"y":0.831},"o":{"x":0.333,"y":0},"t":0,"s":[0,50],"to":[-8.333,-8.333],"ti":[0,16.667]},{"i":{"x":0.833,"y":0.833},"o":{"x":0.167,"y":0.164},"t":11,"s":[-50,0],"to":[0,-16.667],"ti":[-16.667,0]},{"i":{"x":0.833,"y":0.836},"o":{"x":0.167,"y":0.167},"t":22,"s":[0,-50],"to":[16.667,0],"ti":[0,-16.667]},{"i":{"x":0.667,"y":1},"o":{"x":0.167,"y":0.169},"t":33,"s":[50,0],"to":[0,16.667],"ti":[8.333,-8.333]},{"t":44,"s":[0,50]}],"ix":5},"e":{"a":1,"k":[{"i":{"x":0.833,"y":0.831},"o":{"x":0.333,"y":0},"t":0,"s":[0,-50],"to":[8.333,8.333],"ti":[0,-16.667]},{"i":{"x":0.833,"y":0.833},"o":{"x":0.167,"y":0.164},"t":11,"s":[50,0],"to":[0,16.667],"ti":[16.667,0]},{"i":{"x":0.833,"y":0.836},"o":{"x":0.167,"y":0.167},"t":22,"s":[0,50],"to":[-16.667,0],"ti":[0,16.667]},{"i":{"x":0.667,"y":1},"o":{"x":0.167,"y":0.169},"t":33,"s":[-50,0],"to":[0,-16.667],"ti":[-8.333,8.333]},{"t":44,"s":[0,-50]}],"ix":6},"t":1,"nm":"Gradient Fill 1","mn":"ADBE Vector Graphic - G-Fill","hd":false},{"ty":"tr","p":{"a":0,"k":[9.351,-77.955],"ix":2},"a":{"a":0,"k":[0,0],"ix":1},"s":{"a":0,"k":[100,100],"ix":3},"r":{"a":0,"k":0,"ix":6},"o":{"a":0,"k":100,"ix":7},"sk":{"a":0,"k":0,"ix":4},"sa":{"a":0,"k":0,"ix":5},"nm":"Transform"}],"nm":"Ellipse 1","np":2,"cix":2,"bm":0,"ix":1,"mn":"ADBE Vector Group","hd":false}],"ip":0,"op":61,"st":0,"bm":0},{"ddd":0,"ind":2,"ty":4,"nm":"Circle_Inner 2","sr":1,"ks":{"o":{"a":0,"k":100,"ix":11},"r":{"a":0,"k":0,"ix":10},"p":{"a":1,"k":[{"i":{"x":0.833,"y":0.819},"o":{"x":0.333,"y":0},"t":0,"s":[540.186,340.8,0],"to":[-109.455,0,0],"ti":[0,-109.455,0]},{"i":{"x":0.833,"y":0.825},"o":{"x":0.167,"y":0.153},"t":13,"s":[342,538.986,0],"to":[0,109.455,0],"ti":[-109.455,0,0]},{"i":{"x":0.833,"y":0.833},"o":{"x":0.167,"y":0.159},"t":24,"s":[540.186,737.172,0],"to":[109.455,0,0],"ti":[0,109.455,0]},{"i":{"x":0.728,"y":1},"o":{"x":0.167,"y":0.167},"t":34,"s":[738.372,538.986,0],"to":[0,-109.455,0],"ti":[109.455,0,0]},{"t":44,"s":[540.186,340.8,0]}],"ix":2},"a":{"a":0,"k":[9.351,-77.955,0],"ix":1},"s":{"a":0,"k":[50,50,100],"ix":6}},"ao":0,"shapes":[{"ty":"gr","it":[{"d":1,"ty":"el","s":{"a":0,"k":[150,150],"ix":2},"p":{"a":0,"k":[0,0],"ix":3},"nm":"Ellipse Path 1","mn":"ADBE Vector Shape - Ellipse","hd":false},{"ty":"gf","o":{"a":0,"k":100,"ix":10},"r":1,"bm":0,"g":{"p":3,"k":{"a":0,"k":[0,1,0.637,0,0.5,0.998,0.529,0.089,1,0.996,0.421,0.177],"ix":9}},"s":{"a":1,"k":[{"i":{"x":0.833,"y":0.817},"o":{"x":0.333,"y":0},"t":0,"s":[0,50],"to":[-8.333,-8.333],"ti":[0,16.667]},{"i":{"x":0.833,"y":0.825},"o":{"x":0.167,"y":0.151},"t":13,"s":[-50,0],"to":[0,-16.667],"ti":[-16.667,0]},{"i":{"x":0.833,"y":0.836},"o":{"x":0.167,"y":0.159},"t":24,"s":[0,-50],"to":[16.667,0],"ti":[0,-16.667]},{"i":{"x":0.667,"y":1},"o":{"x":0.167,"y":0.169},"t":34,"s":[50,0],"to":[0,16.667],"ti":[8.333,-8.333]},{"t":44,"s":[0,50]}],"ix":5},"e":{"a":1,"k":[{"i":{"x":0.833,"y":0.817},"o":{"x":0.333,"y":0},"t":0,"s":[0,-50],"to":[8.333,8.333],"ti":[0,-16.667]},{"i":{"x":0.833,"y":0.825},"o":{"x":0.167,"y":0.151},"t":13,"s":[50,0],"to":[0,16.667],"ti":[16.667,0]},{"i":{"x":0.833,"y":0.836},"o":{"x":0.167,"y":0.159},"t":24,"s":[0,50],"to":[-16.667,0],"ti":[0,16.667]},{"i":{"x":0.667,"y":1},"o":{"x":0.167,"y":0.169},"t":34,"s":[-50,0],"to":[0,-16.667],"ti":[-8.333,8.333]},{"t":44,"s":[0,-50]}],"ix":6},"t":1,"nm":"Gradient Fill 1","mn":"ADBE Vector Graphic - G-Fill","hd":false},{"ty":"tr","p":{"a":0,"k":[9.351,-77.955],"ix":2},"a":{"a":0,"k":[0,0],"ix":1},"s":{"a":0,"k":[100,100],"ix":3},"r":{"a":0,"k":0,"ix":6},"o":{"a":0,"k":100,"ix":7},"sk":{"a":0,"k":0,"ix":4},"sa":{"a":0,"k":0,"ix":5},"nm":"Transform"}],"nm":"Ellipse 1","np":2,"cix":2,"bm":0,"ix":1,"mn":"ADBE Vector Group","hd":false}],"ip":0,"op":61,"st":0,"bm":0},{"ddd":0,"ind":3,"ty":4,"nm":"Circle_Inner 3","sr":1,"ks":{"o":{"a":0,"k":100,"ix":11},"r":{"a":0,"k":0,"ix":10},"p":{"a":1,"k":[{"i":{"x":0.833,"y":0.8},"o":{"x":0.333,"y":0},"t":0,"s":[540.186,340.8,0],"to":[-109.455,0,0],"ti":[0,-109.455,0]},{"i":{"x":0.833,"y":0.833},"o":{"x":0.167,"y":0.133},"t":15,"s":[342,538.986,0],"to":[0,109.455,0],"ti":[-109.455,0,0]},{"i":{"x":0.833,"y":0.825},"o":{"x":0.167,"y":0.167},"t":25,"s":[540.186,737.172,0],"to":[109.455,0,0],"ti":[0,109.455,0]},{"i":{"x":0.728,"y":1},"o":{"x":0.167,"y":0.158},"t":35,"s":[738.372,538.986,0],"to":[0,-109.455,0],"ti":[109.455,0,0]},{"t":44,"s":[540.186,340.8,0]}],"ix":2},"a":{"a":0,"k":[9.351,-77.955,0],"ix":1},"s":{"a":0,"k":[40,40,100],"ix":6}},"ao":0,"shapes":[{"ty":"gr","it":[{"d":1,"ty":"el","s":{"a":0,"k":[150,150],"ix":2},"p":{"a":0,"k":[0,0],"ix":3},"nm":"Ellipse Path 1","mn":"ADBE Vector Shape - Ellipse","hd":false},{"ty":"gf","o":{"a":0,"k":100,"ix":10},"r":1,"bm":0,"g":{"p":3,"k":{"a":0,"k":[0,1,0.637,0,0.5,0.998,0.529,0.089,1,0.996,0.421,0.177],"ix":9}},"s":{"a":1,"k":[{"i":{"x":0.833,"y":0.797},"o":{"x":0.333,"y":0},"t":0,"s":[0,50],"to":[-8.333,-8.333],"ti":[0,16.667]},{"i":{"x":0.833,"y":0.833},"o":{"x":0.167,"y":0.131},"t":15,"s":[-50,0],"to":[0,-16.667],"ti":[-16.667,0]},{"i":{"x":0.833,"y":0.827},"o":{"x":0.167,"y":0.167},"t":25,"s":[0,-50],"to":[16.667,0],"ti":[0,-16.667]},{"i":{"x":0.667,"y":1},"o":{"x":0.167,"y":0.16},"t":35,"s":[50,0],"to":[0,16.667],"ti":[8.333,-8.333]},{"t":44,"s":[0,50]}],"ix":5},"e":{"a":1,"k":[{"i":{"x":0.833,"y":0.797},"o":{"x":0.333,"y":0},"t":0,"s":[0,-50],"to":[8.333,8.333],"ti":[0,-16.667]},{"i":{"x":0.833,"y":0.833},"o":{"x":0.167,"y":0.131},"t":15,"s":[50,0],"to":[0,16.667],"ti":[16.667,0]},{"i":{"x":0.833,"y":0.827},"o":{"x":0.167,"y":0.167},"t":25,"s":[0,50],"to":[-16.667,0],"ti":[0,16.667]},{"i":{"x":0.667,"y":1},"o":{"x":0.167,"y":0.16},"t":35,"s":[-50,0],"to":[0,-16.667],"ti":[-8.333,8.333]},{"t":44,"s":[0,-50]}],"ix":6},"t":1,"nm":"Gradient Fill 1","mn":"ADBE Vector Graphic - G-Fill","hd":false},{"ty":"tr","p":{"a":0,"k":[9.351,-77.955],"ix":2},"a":{"a":0,"k":[0,0],"ix":1},"s":{"a":0,"k":[100,100],"ix":3},"r":{"a":0,"k":0,"ix":6},"o":{"a":0,"k":100,"ix":7},"sk":{"a":0,"k":0,"ix":4},"sa":{"a":0,"k":0,"ix":5},"nm":"Transform"}],"nm":"Ellipse 1","np":2,"cix":2,"bm":0,"ix":1,"mn":"ADBE Vector Group","hd":false}],"ip":0,"op":61,"st":0,"bm":0},{"ddd":0,"ind":4,"ty":4,"nm":"Circle_Outer 1","sr":1,"ks":{"o":{"a":0,"k":100,"ix":11},"r":{"a":0,"k":0,"ix":10},"p":{"a":1,"k":[{"i":{"x":0.833,"y":0.833},"o":{"x":0.272,"y":0},"t":0,"s":[540.31,208,0],"to":[182.425,0,0],"ti":[0,-182.425,0]},{"i":{"x":0.833,"y":0.833},"o":{"x":0.167,"y":0.167},"t":11,"s":[870.62,538.31,0],"to":[0,182.425,0],"ti":[182.425,0,0]},{"i":{"x":0.833,"y":0.833},"o":{"x":0.167,"y":0.167},"t":22,"s":[540.31,868.62,0],"to":[-182.425,0,0],"ti":[0,182.425,0]},{"i":{"x":0.667,"y":1},"o":{"x":0.167,"y":0.167},"t":33,"s":[210,538.31,0],"to":[0,-182.425,0],"ti":[-182.425,0,0]},{"t":44,"s":[540.31,208,0]}],"ix":2},"a":{"a":0,"k":[9.351,-77.955,0],"ix":1},"s":{"a":0,"k":[100,100,100],"ix":6}},"ao":0,"shapes":[{"ty":"gr","it":[{"d":1,"ty":"el","s":{"a":0,"k":[150,150],"ix":2},"p":{"a":0,"k":[0,0],"ix":3},"nm":"Ellipse Path 1","mn":"ADBE Vector Shape - Ellipse","hd":false},{"ty":"gf","o":{"a":0,"k":100,"ix":10},"r":1,"bm":0,"g":{"p":3,"k":{"a":0,"k":[0,0.996,0.421,0.177,0.5,0.998,0.529,0.089,1,1,0.637,0],"ix":9}},"s":{"a":1,"k":[{"i":{"x":0.833,"y":0.831},"o":{"x":0.333,"y":0},"t":0,"s":[0,100],"to":[-16.667,-16.667],"ti":[0,33.333]},{"i":{"x":0.833,"y":0.833},"o":{"x":0.167,"y":0.164},"t":11,"s":[-100,0],"to":[0,-33.333],"ti":[-33.333,0]},{"i":{"x":0.833,"y":0.836},"o":{"x":0.167,"y":0.167},"t":22,"s":[0,-100],"to":[33.333,0],"ti":[0,-33.333]},{"i":{"x":0.667,"y":1},"o":{"x":0.167,"y":0.169},"t":33,"s":[100,0],"to":[0,33.333],"ti":[16.667,-16.667]},{"t":44,"s":[0,100]}],"ix":5},"e":{"a":0,"k":[0,0],"ix":6},"t":1,"nm":"Gradient Fill 1","mn":"ADBE Vector Graphic - G-Fill","hd":false},{"ty":"tr","p":{"a":0,"k":[9.351,-77.955],"ix":2},"a":{"a":0,"k":[0,0],"ix":1},"s":{"a":0,"k":[100,100],"ix":3},"r":{"a":0,"k":0,"ix":6},"o":{"a":0,"k":100,"ix":7},"sk":{"a":0,"k":0,"ix":4},"sa":{"a":0,"k":0,"ix":5},"nm":"Transform"}],"nm":"Ellipse 1","np":2,"cix":2,"bm":0,"ix":1,"mn":"ADBE Vector Group","hd":false}],"ip":0,"op":61,"st":0,"bm":0},{"ddd":0,"ind":5,"ty":4,"nm":"Circle_Outer 5","sr":1,"ks":{"o":{"a":0,"k":100,"ix":11},"r":{"a":0,"k":0,"ix":10},"p":{"a":1,"k":[{"i":{"x":0.833,"y":0.819},"o":{"x":0.272,"y":0},"t":0,"s":[540.31,208,0],"to":[182.425,0,0],"ti":[0,-182.425,0]},{"i":{"x":0.833,"y":0.825},"o":{"x":0.167,"y":0.153},"t":13,"s":[870.62,538.31,0],"to":[0,182.425,0],"ti":[182.425,0,0]},{"i":{"x":0.833,"y":0.833},"o":{"x":0.167,"y":0.159},"t":24,"s":[540.31,868.62,0],"to":[-182.425,0,0],"ti":[0,182.425,0]},{"i":{"x":0.667,"y":1},"o":{"x":0.167,"y":0.167},"t":34,"s":[210,538.31,0],"to":[0,-182.425,0],"ti":[-182.425,0,0]},{"t":44,"s":[540.31,208,0]}],"ix":2},"a":{"a":0,"k":[9.351,-77.955,0],"ix":1},"s":{"a":0,"k":[90,90,100],"ix":6}},"ao":0,"shapes":[{"ty":"gr","it":[{"d":1,"ty":"el","s":{"a":0,"k":[150,150],"ix":2},"p":{"a":0,"k":[0,0],"ix":3},"nm":"Ellipse Path 1","mn":"ADBE Vector Shape - Ellipse","hd":false},{"ty":"gf","o":{"a":0,"k":100,"ix":10},"r":1,"bm":0,"g":{"p":3,"k":{"a":0,"k":[0,0.996,0.421,0.177,0.5,0.998,0.529,0.089,1,1,0.637,0],"ix":9}},"s":{"a":1,"k":[{"i":{"x":0.833,"y":0.817},"o":{"x":0.333,"y":0},"t":0,"s":[0,100],"to":[-16.667,-16.667],"ti":[0,33.333]},{"i":{"x":0.833,"y":0.825},"o":{"x":0.167,"y":0.151},"t":13,"s":[-100,0],"to":[0,-33.333],"ti":[-33.333,0]},{"i":{"x":0.833,"y":0.836},"o":{"x":0.167,"y":0.159},"t":24,"s":[0,-100],"to":[33.333,0],"ti":[0,-33.333]},{"i":{"x":0.667,"y":1},"o":{"x":0.167,"y":0.169},"t":34,"s":[100,0],"to":[0,33.333],"ti":[16.667,-16.667]},{"t":44,"s":[0,100]}],"ix":5},"e":{"a":0,"k":[0,0],"ix":6},"t":1,"nm":"Gradient Fill 1","mn":"ADBE Vector Graphic - G-Fill","hd":false},{"ty":"tr","p":{"a":0,"k":[9.351,-77.955],"ix":2},"a":{"a":0,"k":[0,0],"ix":1},"s":{"a":0,"k":[100,100],"ix":3},"r":{"a":0,"k":0,"ix":6},"o":{"a":0,"k":100,"ix":7},"sk":{"a":0,"k":0,"ix":4},"sa":{"a":0,"k":0,"ix":5},"nm":"Transform"}],"nm":"Ellipse 1","np":2,"cix":2,"bm":0,"ix":1,"mn":"ADBE Vector Group","hd":false}],"ip":0,"op":61,"st":0,"bm":0},{"ddd":0,"ind":6,"ty":4,"nm":"Circle_Outer 2","sr":1,"ks":{"o":{"a":0,"k":100,"ix":11},"r":{"a":0,"k":0,"ix":10},"p":{"a":1,"k":[{"i":{"x":0.833,"y":0.819},"o":{"x":0.272,"y":0},"t":0,"s":[540.31,208,0],"to":[182.425,0,0],"ti":[0,-182.425,0]},{"i":{"x":0.833,"y":0.825},"o":{"x":0.167,"y":0.153},"t":13,"s":[870.62,538.31,0],"to":[0,182.425,0],"ti":[182.425,0,0]},{"i":{"x":0.833,"y":0.833},"o":{"x":0.167,"y":0.159},"t":24,"s":[540.31,868.62,0],"to":[-182.425,0,0],"ti":[0,182.425,0]},{"i":{"x":0.667,"y":1},"o":{"x":0.167,"y":0.167},"t":34,"s":[210,538.31,0],"to":[0,-182.425,0],"ti":[-182.425,0,0]},{"t":44,"s":[540.31,208,0]}],"ix":2},"a":{"a":0,"k":[9.351,-77.955,0],"ix":1},"s":{"a":0,"k":[90,90,100],"ix":6}},"ao":0,"shapes":[{"ty":"gr","it":[{"d":1,"ty":"el","s":{"a":0,"k":[150,150],"ix":2},"p":{"a":0,"k":[0,0],"ix":3},"nm":"Ellipse Path 1","mn":"ADBE Vector Shape - Ellipse","hd":false},{"ty":"gf","o":{"a":0,"k":100,"ix":10},"r":1,"bm":0,"g":{"p":3,"k":{"a":0,"k":[0,0.996,0.421,0.177,0.5,0.998,0.529,0.089,1,1,0.637,0],"ix":9}},"s":{"a":1,"k":[{"i":{"x":0.833,"y":0.817},"o":{"x":0.333,"y":0},"t":0,"s":[0,100],"to":[-16.667,-16.667],"ti":[0,33.333]},{"i":{"x":0.833,"y":0.825},"o":{"x":0.167,"y":0.151},"t":13,"s":[-100,0],"to":[0,-33.333],"ti":[-33.333,0]},{"i":{"x":0.833,"y":0.836},"o":{"x":0.167,"y":0.159},"t":24,"s":[0,-100],"to":[33.333,0],"ti":[0,-33.333]},{"i":{"x":0.667,"y":1},"o":{"x":0.167,"y":0.169},"t":34,"s":[100,0],"to":[0,33.333],"ti":[16.667,-16.667]},{"t":44,"s":[0,100]}],"ix":5},"e":{"a":0,"k":[0,0],"ix":6},"t":1,"nm":"Gradient Fill 1","mn":"ADBE Vector Graphic - G-Fill","hd":false},{"ty":"tr","p":{"a":0,"k":[9.351,-77.955],"ix":2},"a":{"a":0,"k":[0,0],"ix":1},"s":{"a":0,"k":[100,100],"ix":3},"r":{"a":0,"k":0,"ix":6},"o":{"a":0,"k":100,"ix":7},"sk":{"a":0,"k":0,"ix":4},"sa":{"a":0,"k":0,"ix":5},"nm":"Transform"}],"nm":"Ellipse 1","np":2,"cix":2,"bm":0,"ix":1,"mn":"ADBE Vector Group","hd":false}],"ip":0,"op":61,"st":0,"bm":0},{"ddd":0,"ind":7,"ty":4,"nm":"Circle_Outer 3","sr":1,"ks":{"o":{"a":0,"k":100,"ix":11},"r":{"a":0,"k":0,"ix":10},"p":{"a":1,"k":[{"i":{"x":0.833,"y":0.808},"o":{"x":0.272,"y":0},"t":0,"s":[540.31,208,0],"to":[182.425,0,0],"ti":[0,-182.425,0]},{"i":{"x":0.833,"y":0.817},"o":{"x":0.167,"y":0.141},"t":15,"s":[870.62,538.31,0],"to":[0,182.425,0],"ti":[182.425,0,0]},{"i":{"x":0.833,"y":0.833},"o":{"x":0.167,"y":0.15},"t":26,"s":[540.31,868.62,0],"to":[-182.425,0,0],"ti":[0,182.425,0]},{"i":{"x":0.667,"y":1},"o":{"x":0.167,"y":0.167},"t":35,"s":[210,538.31,0],"to":[0,-182.425,0],"ti":[-182.425,0,0]},{"t":44,"s":[540.31,208,0]}],"ix":2},"a":{"a":0,"k":[9.351,-77.955,0],"ix":1},"s":{"a":0,"k":[80,80,100],"ix":6}},"ao":0,"shapes":[{"ty":"gr","it":[{"d":1,"ty":"el","s":{"a":0,"k":[150,150],"ix":2},"p":{"a":0,"k":[0,0],"ix":3},"nm":"Ellipse Path 1","mn":"ADBE Vector Shape - Ellipse","hd":false},{"ty":"gf","o":{"a":0,"k":100,"ix":10},"r":1,"bm":0,"g":{"p":3,"k":{"a":0,"k":[0,0.996,0.421,0.177,0.5,0.998,0.529,0.089,1,1,0.637,0],"ix":9}},"s":{"a":1,"k":[{"i":{"x":0.833,"y":0.805},"o":{"x":0.333,"y":0},"t":0,"s":[0,100],"to":[-16.667,-16.667],"ti":[0,33.333]},{"i":{"x":0.833,"y":0.817},"o":{"x":0.167,"y":0.139},"t":15,"s":[-100,0],"to":[0,-33.333],"ti":[-33.333,0]},{"i":{"x":0.833,"y":0.836},"o":{"x":0.167,"y":0.15},"t":26,"s":[0,-100],"to":[33.333,0],"ti":[0,-33.333]},{"i":{"x":0.667,"y":1},"o":{"x":0.167,"y":0.169},"t":35,"s":[100,0],"to":[0,33.333],"ti":[16.667,-16.667]},{"t":44,"s":[0,100]}],"ix":5},"e":{"a":0,"k":[0,0],"ix":6},"t":1,"nm":"Gradient Fill 1","mn":"ADBE Vector Graphic - G-Fill","hd":false},{"ty":"tr","p":{"a":0,"k":[9.351,-77.955],"ix":2},"a":{"a":0,"k":[0,0],"ix":1},"s":{"a":0,"k":[100,100],"ix":3},"r":{"a":0,"k":0,"ix":6},"o":{"a":0,"k":100,"ix":7},"sk":{"a":0,"k":0,"ix":4},"sa":{"a":0,"k":0,"ix":5},"nm":"Transform"}],"nm":"Ellipse 1","np":2,"cix":2,"bm":0,"ix":1,"mn":"ADBE Vector Group","hd":false}],"ip":0,"op":61,"st":0,"bm":0},{"ddd":0,"ind":8,"ty":4,"nm":"Circle_Outer 4","sr":1,"ks":{"o":{"a":0,"k":100,"ix":11},"r":{"a":0,"k":0,"ix":10},"p":{"a":1,"k":[{"i":{"x":0.833,"y":0.79},"o":{"x":0.272,"y":0},"t":0,"s":[540.31,208,0],"to":[182.425,0,0],"ti":[0,-182.425,0]},{"i":{"x":0.833,"y":0.825},"o":{"x":0.167,"y":0.123},"t":17,"s":[870.62,538.31,0],"to":[0,182.425,0],"ti":[182.425,0,0]},{"i":{"x":0.833,"y":0.824},"o":{"x":0.167,"y":0.158},"t":27,"s":[540.31,868.62,0],"to":[-182.425,0,0],"ti":[0,182.425,0]},{"i":{"x":0.667,"y":1},"o":{"x":0.167,"y":0.157},"t":36,"s":[210,538.31,0],"to":[0,-182.425,0],"ti":[-182.425,0,0]},{"t":44,"s":[540.31,208,0]}],"ix":2},"a":{"a":0,"k":[9.351,-77.955,0],"ix":1},"s":{"a":0,"k":[70,70,100],"ix":6}},"ao":0,"shapes":[{"ty":"gr","it":[{"d":1,"ty":"el","s":{"a":0,"k":[150,150],"ix":2},"p":{"a":0,"k":[0,0],"ix":3},"nm":"Ellipse Path 1","mn":"ADBE Vector Shape - Ellipse","hd":false},{"ty":"gf","o":{"a":0,"k":100,"ix":10},"r":1,"bm":0,"g":{"p":3,"k":{"a":0,"k":[0,0.996,0.421,0.177,0.5,0.998,0.529,0.089,1,1,0.637,0],"ix":9}},"s":{"a":1,"k":[{"i":{"x":0.833,"y":0.787},"o":{"x":0.333,"y":0},"t":0,"s":[0,100],"to":[-16.667,-16.667],"ti":[0,33.333]},{"i":{"x":0.833,"y":0.825},"o":{"x":0.167,"y":0.122},"t":17,"s":[-100,0],"to":[0,-33.333],"ti":[-33.333,0]},{"i":{"x":0.833,"y":0.826},"o":{"x":0.167,"y":0.158},"t":27,"s":[0,-100],"to":[33.333,0],"ti":[0,-33.333]},{"i":{"x":0.667,"y":1},"o":{"x":0.167,"y":0.159},"t":36,"s":[100,0],"to":[0,33.333],"ti":[16.667,-16.667]},{"t":44,"s":[0,100]}],"ix":5},"e":{"a":0,"k":[0,0],"ix":6},"t":1,"nm":"Gradient Fill 1","mn":"ADBE Vector Graphic - G-Fill","hd":false},{"ty":"tr","p":{"a":0,"k":[9.351,-77.955],"ix":2},"a":{"a":0,"k":[0,0],"ix":1},"s":{"a":0,"k":[100,100],"ix":3},"r":{"a":0,"k":0,"ix":6},"o":{"a":0,"k":100,"ix":7},"sk":{"a":0,"k":0,"ix":4},"sa":{"a":0,"k":0,"ix":5},"nm":"Transform"}],"nm":"Ellipse 1","np":2,"cix":2,"bm":0,"ix":1,"mn":"ADBE Vector Group","hd":false}],"ip":0,"op":61,"st":0,"bm":0}],"markers":[]}